ko_lm_dataformat/__init__.py
ko_lm_dataformat/archive.py
ko_lm_dataformat/reader.py
ko_lm_dataformat/sentence_cleaner.py
ko_lm_dataformat/sentence_splitter.py
ko_lm_dataformat/utils.py
ko_lm_dataformat-0.3.1.dist-info/METADATA
ko_lm_dataformat-0.3.1.dist-info/WHEEL
ko_lm_dataformat-0.3.1.dist-info/licenses/LICENSE
ko_lm_dataformat-0.3.1.dist-info/RECORD
