Metadata-Version: 2.4
Name: ko_lm_dataformat
Version: 0.3.1
Summary: A utility for storing and reading files for Korean LM training.
Author-email: Jangwon Park <adieujw@gmail.com>
License-Expression: MIT
License-File: LICENSE
Classifier: Programming Language :: Python :: 3
Classifier: Programming Language :: Python :: 3.9
Classifier: Programming Language :: Python :: 3.10
Classifier: Programming Language :: Python :: 3.11
Classifier: Programming Language :: Python :: 3.12
Classifier: Programming Language :: Python :: 3.13
Requires-Python: <4.0,>=3.9
Requires-Dist: jsonlines
Requires-Dist: packaging
Requires-Dist: ujson
Requires-Dist: zstandard
